kelvin_icd-6.1.0-py3.8-nspkg.pth
kelvin/icd/__init__.py
kelvin/icd/__main__.py
kelvin/icd/exception.py
kelvin/icd/icd.py
kelvin/icd/message.py
kelvin/icd/model.py
kelvin/icd/package.py
kelvin/icd/py.typed
kelvin/icd/types.py
kelvin/icd/utils.py
kelvin/icd/version.py
kelvin/icd/cli/__init__.py
kelvin/icd/cli/main.py
kelvin/icd/cli/message.py
kelvin/icd/vendor/__init__.py
kelvin/icd/vendor/pyrobuf/__init__.py
kelvin/icd/vendor/pyrobuf/parse_proto.py
kelvin_icd-6.1.0.dist-info/LICENSE.rst
kelvin_icd-6.1.0.dist-info/METADATA
kelvin_icd-6.1.0.dist-info/WHEEL
kelvin_icd-6.1.0.dist-info/entry_points.txt
kelvin_icd-6.1.0.dist-info/namespace_packages.txt
kelvin_icd-6.1.0.dist-info/top_level.txt
kelvin_icd-6.1.0.dist-info/RECORD
