Metadata-Version: 2.1
Name: kelvin-icd
Version: 6.1.0
Summary: Kelvin ICD
Home-page: https://kelvininc.com/
Author: Kelvin Inc
Author-email: engineering@kelvininc.com
License: UNKNOWN
Platform: any
Classifier: Operating System :: OS Independent
Classifier: Programming Language :: Python :: 3.7
Classifier: Programming Language :: Python :: 3.8
Classifier: Programming Language :: Python :: 3.9
Requires-Python: <3.10,>=3.7.0
License-File: LICENSE.rst
Requires-Dist: orjson (==3.4.*)
Requires-Dist: pydantic[email] (==1.7.*)
Requires-Dist: cloudevents (==1.2.*)
Provides-Extra: builder
Requires-Dist: black (==20.8b1) ; extra == 'builder'
Requires-Dist: click (==7.1.2) ; extra == 'builder'
Requires-Dist: click-shell (==2.0) ; extra == 'builder'
Requires-Dist: isort (==5.7.*) ; extra == 'builder'
Requires-Dist: PyYAML (==5.4.*) ; extra == 'builder'
Requires-Dist: wheel (>=0.34.2) ; extra == 'builder'
Requires-Dist: xdg (>=5.0.0) ; extra == 'builder'
Provides-Extra: development
Requires-Dist: pre-commit ; extra == 'development'
Provides-Extra: docs
Requires-Dist: Sphinx ; extra == 'docs'
Requires-Dist: sphinx-autodoc-typehints ; extra == 'docs'
Requires-Dist: sphinx-rtd-theme ; extra == 'docs'
Requires-Dist: ipython ; extra == 'docs'
Provides-Extra: format
Requires-Dist: isort ; extra == 'format'
Requires-Dist: black ; extra == 'format'
Provides-Extra: lint
Requires-Dist: flake8 (==3.8.*) ; extra == 'lint'
Requires-Dist: flake8-print (==4.0.*) ; extra == 'lint'
Requires-Dist: flake8-isort (==4.0.*) ; extra == 'lint'
Requires-Dist: pep8-naming (==0.11.*) ; extra == 'lint'
Requires-Dist: mypy (==0.910) ; extra == 'lint'
Requires-Dist: lxml (==4.6.3) ; extra == 'lint'
Requires-Dist: types-PyYAML (==5.4.*) ; extra == 'lint'
Requires-Dist: types-orjson (==0.1.*) ; extra == 'lint'
Provides-Extra: security
Requires-Dist: bandit (==1.7.*) ; extra == 'security'
Requires-Dist: safety (==1.10.*) ; extra == 'security'
Provides-Extra: tests
Requires-Dist: ipython ; extra == 'tests'
Requires-Dist: pytest (>=6.0.1) ; extra == 'tests'
Requires-Dist: pytest-cov (==2.8.1) ; extra == 'tests'
Requires-Dist: pytest-benchmark (==3.2.3) ; extra == 'tests'
Requires-Dist: pytest-codestyle (==2.0.1) ; extra == 'tests'
Requires-Dist: pytest-flakes (==4.0.0) ; extra == 'tests'
Requires-Dist: pytest-html (==2.1.1) ; extra == 'tests'
Requires-Dist: pytest-mypy (==0.6.1) ; extra == 'tests'
Requires-Dist: pytest-timeout (==1.3.4) ; extra == 'tests'
Requires-Dist: pytest-xdist (==1.32.0) ; extra == 'tests'
Requires-Dist: pytest-virtualenv (==1.7.0) ; extra == 'tests'
Provides-Extra: wheel
Requires-Dist: wheel (>=0.34.2) ; extra == 'wheel'
Requires-Dist: twine ; extra == 'wheel'
